python/trackforge.pyi
trackforge-0.1.8.dist-info/METADATA
trackforge-0.1.8.dist-info/WHEEL
trackforge-0.1.8.dist-info/licenses/LICENSE
trackforge/__init__.py
trackforge/trackforge.cpython-312-arm-linux-gnueabihf.so
trackforge-0.1.8.dist-info/RECORD
