Metadata-Version: 2.4
Name: trackforge
Version: 0.1.8
Classifier: Programming Language :: Rust
Classifier: Programming Language :: Python :: Implementation :: CPython
Classifier: Programming Language :: Python :: Implementation :: PyPy
Classifier: Topic :: Scientific/Engineering :: Image Recognition
Classifier: Topic :: Scientific/Engineering :: Artificial Intelligence
Classifier: License :: OSI Approved :: MIT License
License-File: LICENSE
Summary: A unified, high-performance computer vision tracking library.
Home-Page: https://github.com/onuralpszr/trackforge
Author-email: Onuralp Sezer <thunderbirdtr@gmail.com>
License: MIT
Requires-Python: >=3.7
